triogram/__init__.py
triogram/api.py
triogram/bot.py
triogram/config.py
triogram/errors.py
triogram/fanout.py
triogram/http.py
triogram/updater.py
triogram-0.6.0.dist-info/METADATA
triogram-0.6.0.dist-info/WHEEL
triogram-0.6.0.dist-info/top_level.txt
triogram-0.6.0.dist-info/RECORD
